pydprint/__init__.py
pydprint/dprint.py
pydprint-0.0.4.dist-info/LICENSE
pydprint-0.0.4.dist-info/METADATA
pydprint-0.0.4.dist-info/WHEEL
pydprint-0.0.4.dist-info/top_level.txt
pydprint-0.0.4.dist-info/RECORD
