Metadata-Version: 2.1
Name: pydprint
Version: 0.0.4
Summary: An easy-to-use debug print tool for deep learning studies in python.
Home-page: https://github.com/chaoyivision/python-dprint
Author: Chaoyi ZHANG
Author-email: chaoyivision@gmail.com
License: UNKNOWN
Project-URL: Bug Tracker, https://github.com/chaoyivision/python-dprint/issues
Platform: UNKNOWN
Classifier: Programming Language :: Python :: 3
Classifier: License :: OSI Approved :: MIT License
Classifier: Operating System :: OS Independent
Requires-Python: >=3.6
License-File: LICENSE
